{"acidophilic.false":0.806493,"acidophilic.unannotated":0.156966,"acidophilic.unclassified":0.034784,"aerobic_growth_anoxygenic_phototrophy.false":0.717749,"aerobic_growth_anoxygenic_phototrophy.no_majority":0.08792,"aerobic_growth_anoxygenic_phototrophy.true":0.000824,"aerobic_growth_anoxygenic_phototrophy.unannotated":0.156966,"aerobic_growth_anoxygenic_phototrophy.unclassified":0.034784,"aerotolerant.false":0.013658,"aerotolerant.no_majority":0.176006,"aerotolerant.true":0.755786,"aerotolerant.unannotated":0.01801,"aerotolerant.unclassified":0.034784,"ammonification_nitrate.false":0.806301,"ammonification_nitrate.true":0.000192,"ammonification_nitrate.unannotated":0.156966,"ammonification_nitrate.unclassified":0.034784,"ammonification_nitrite.false":0.806301,"ammonification_nitrite.true":0.000192,"ammonification_nitrite.unannotated":0.156966,"ammonification_nitrite.unclassified":0.034784,"assimilation_agar.false":0.000137,"assimilation_agar.unannotated":0.963322,"assimilation_agar.unclassified":0.034784,"assimilation_benzene.false":0.001688,"assimilation_benzene.true":0.024722,"assimilation_benzene.unannotated":0.937049,"assimilation_benzene.unclassified":0.034784,"assimilation_casein.false":0.022539,"assimilation_casein.true":0.004502,"assimilation_casein.unannotated":0.936417,"assimilation_casein.unclassified":0.034784,"assimilation_cellobiose.false":0.01278,"assimilation_cellobiose.no_majority":0.034194,"assimilation_cellobiose.true":0.047179,"assimilation_cellobiose.unannotated":0.869307,"assimilation_cellobiose.unclassified":0.034784,"assimilation_cellulose.false":0.033617,"assimilation_cellulose.unannotated":0.929842,"assimilation_cellulose.unclassified":0.034784,"assimilation_chitin.true":0.022402,"assimilation_chitin.unannotated":0.941057,"assimilation_chitin.unclassified":0.034784,"assimilation_chitosan.true":0.022402,"assimilation_chitosan.unannotated":0.941057,"assimilation_chitosan.unclassified":0.034784,"assimilation_dextrin.true":0.000165,"assimilation_dextrin.unannotated":0.963295,"assimilation_dextrin.unclassified":0.034784,"assimilation_gelatin.false":0.002938,"assimilation_gelatin.no_majority":0.022402,"assimilation_gelatin.true":0.026836,"assimilation_gelatin.unannotated":0.911284,"assimilation_gelatin.unclassified":0.034784,"assimilation_glycogen.true":0.002718,"assimilation_glycogen.unannotated":0.960741,"assimilation_glycogen.unclassified":0.034784,"builds_gas_from_nitrate.false":0.005463,"builds_gas_from_nitrate.true":0.001428,"builds_gas_from_nitrate.unannotated":0.956568,"builds_gas_from_nitrate.unclassified":0.034784,"builds_gas_from_nitrite.false":0.005463,"builds_gas_from_nitrite.true":0.001428,"builds_gas_from_nitrite.unannotated":0.956568,"builds_gas_from_nitrite.unclassified":0.034784,"capnophilic.false":0.651558,"capnophilic.no_majority":0.105861,"capnophilic.true":0.005944,"capnophilic.unannotated":0.200096,"capnophilic.unclassified":0.034784,"carbon_source_alginate.false":0.010309,"carbon_source_alginate.unannotated":0.95315,"carbon_source_alginate.unclassified":0.034784,"carbon_source_alpha_cyclodextrin.false":0.000137,"carbon_source_alpha_cyclodextrin.true":0.02652,"carbon_source_alpha_cyclodextrin.unannotated":0.936802,"carbon_source_alpha_cyclodextrin.unclassified":0.034784,"carbon_source_beta_cyclodextrin.false":0.000137,"carbon_source_beta_cyclodextrin.unannotated":0.963322,"carbon_source_beta_cyclodextrin.unclassified":0.034784,"carbon_source_cellobiose.false":0.034564,"carbon_source_cellobiose.no_majority":0.006726,"carbon_source_cellobiose.true":0.186465,"carbon_source_cellobiose.unannotated":0.735704,"carbon_source_cellobiose.unclassified":0.034784,"carbon_source_cellulose.false":0.004502,"carbon_source_cellulose.no_majority":0.022402,"carbon_source_cellulose.true":0.002841,"carbon_source_cellulose.unannotated":0.933713,"carbon_source_cellulose.unclassified":0.034784,"carbon_source_chitosan.false":0.000728,"carbon_source_chitosan.no_majority":0.022402,"carbon_source_chitosan.unannotated":0.94033,"carbon_source_chitosan.unclassified":0.034784,"carbon_source_dextran.false":0.001688,"carbon_source_dextran.unannotated":0.961771,"carbon_source_dextran.unclassified":0.034784,"carbon_source_dextrin.no_majority":0.000151,"carbon_source_dextrin.true":0.102141,"carbon_source_dextrin.unannotated":0.861167,"carbon_source_dextrin.unclassified":0.034784,"carbon_source_gelatin.true":0.071229,"carbon_source_gelatin.unannotated":0.892231,"carbon_source_gelatin.unclassified":0.034784,"carbon_source_glycogen.no_majority":0.006452,"carbon_source_glycogen.true":0.099437,"carbon_source_glycogen.unannotated":0.85757,"carbon_source_glycogen.unclassified":0.034784,"carbon_source_starch.false":0.022402,"carbon_source_starch.unannotated":0.941057,"carbon_source_starch.unclassified":0.034784,"degradation_agar.false":0.00442,"degradation_agar.unannotated":0.959039,"degradation_agar.unclassified":0.034784,"degradation_alginate.false":0.000618,"degradation_alginate.true":0.005532,"degradation_alginate.unannotated":0.95731,"degradation_alginate.unclassified":0.034784,"degradation_aromatic_compound.false":0.798572,"degradation_aromatic_compound.true":0.00792,"degradation_aromatic_compound.unannotated":0.156966,"degradation_aromatic_compound.unclassified":0.034784,"degradation_aromatic_hydrocarbon.false":0.805052,"degradation_aromatic_hydrocarbon.no_majority":0.000329,"degradation_aromatic_hydrocarbon.true":0.001112,"degradation_aromatic_hydrocarbon.unannotated":0.156966,"degradation_aromatic_hydrocarbon.unclassified":0.034784,"degradation_benzoate.false":0.004502,"degradation_benzoate.unannotated":0.958957,"degradation_benzoate.unclassified":0.034784,"degradation_carboxymethylcellulose.false":0.035649,"degradation_carboxymethylcellulose.true":0.006932,"degradation_carboxymethylcellulose.unannotated":0.920879,"degradation_carboxymethylcellulose.unclassified":0.034784,"degradation_casein.false":0.009691,"degradation_casein.no_majority":0.024091,"degradation_casein.true":0.018435,"degradation_casein.unannotated":0.911242,"degradation_casein.unclassified":0.034784,"degradation_cellobiose.false":0.029705,"degradation_cellobiose.no_majority":0.001839,"degradation_cellobiose.unannotated":0.931915,"degradation_cellobiose.unclassified":0.034784,"degradation_cellulose.false":0.759657,"degradation_cellulose.no_majority":0.045752,"degradation_cellulose.true":0.004379,"degradation_cellulose.unannotated":0.153672,"degradation_cellulose.unclassified":0.034784,"degradation_chitin.false":0.734166,"degradation_chitin.no_majority":0.072162,"degradation_chitin.true":0.003459,"degradation_chitin.unannotated":0.153672,"degradation_chitin.unclassified":0.034784,"degradation_chitosan.false":0.001757,"degradation_chitosan.unannotated":0.961702,"degradation_chitosan.unclassified":0.034784,"degradation_dna.true":0.001757,"degradation_dna.unannotated":0.961702,"degradation_dna.unclassified":0.034784,"degradation_gelatin.false":0.005806,"degradation_gelatin.no_majority":0.022402,"degradation_gelatin.true":0.004763,"degradation_gelatin.unannotated":0.930487,"degradation_gelatin.unclassified":0.034784,"degradation_glycogen.false":0.000275,"degradation_glycogen.unannotated":0.963185,"degradation_glycogen.unclassified":0.034784,"degradation_hydrocarbon.false":0.801428,"degradation_hydrocarbon.no_majority":0.002018,"degradation_hydrocarbon.true":0.003047,"degradation_hydrocarbon.unannotated":0.156966,"degradation_hydrocarbon.unclassified":0.034784,"degradation_lignin.false":0.801181,"degradation_lignin.no_majority":0.004859,"degradation_lignin.true":0.000453,"degradation_lignin.unannotated":0.156966,"degradation_lignin.unclassified":0.034784,"degradation_milk.false":0.000151,"degradation_milk.unannotated":0.963308,"degradation_milk.unclassified":0.034784,"degradation_phenol.false":0.006452,"degradation_phenol.true":0.000178,"degradation_phenol.unannotated":0.956829,"degradation_phenol.unclassified":0.034784,"degradation_plastic.false":0.796747,"degradation_plastic.no_majority":0.009746,"degradation_plastic.unannotated":0.156966,"degradation_plastic.unclassified":0.034784,"degradation_skimmed_milk.true":0.022402,"degradation_skimmed_milk.unannotated":0.941057,"degradation_skimmed_milk.unclassified":0.034784,"degradation_starch.false":0.001153,"degradation_starch.unannotated":0.962306,"degradation_starch.unclassified":0.034784,"denitrification_nitrate.false":0.752478,"denitrification_nitrate.no_majority":0.045848,"denitrification_nitrate.true":0.008167,"denitrification_nitrate.unannotated":0.156966,"denitrification_nitrate.unclassified":0.034784,"denitrification_nitrite.false":0.802045,"denitrification_nitrite.no_majority":0.004447,"denitrification_nitrite.unannotated":0.156966,"denitrification_nitrite.unclassified":0.034784,"denitrification_nitrous_oxide.false":0.75801,"denitrification_nitrous_oxide.no_majority":0.044887,"denitrification_nitrous_oxide.true":0.003596,"denitrification_nitrous_oxide.unannotated":0.156966,"denitrification_nitrous_oxide.unclassified":0.034784,"denitrification_pathway.false":0.802045,"denitrification_pathway.no_majority":0.004447,"denitrification_pathway.unannotated":0.156966,"denitrification_pathway.unclassified":0.034784,"electron_acceptor_elemental_sulfur.false":0.805408,"electron_acceptor_elemental_sulfur.no_majority":0.000782,"electron_acceptor_elemental_sulfur.true":0.000755,"electron_acceptor_elemental_sulfur.unannotated":0.156513,"electron_acceptor_elemental_sulfur.unclassified":0.034784,"electron_acceptor_manganese.false":0.806493,"electron_acceptor_manganese.unannotated":0.156966,"electron_acceptor_manganese.unclassified":0.034784,"electron_acceptor_sulfate.false":0.800494,"electron_acceptor_sulfate.no_majority":0.001592,"electron_acceptor_sulfate.true":0.004406,"electron_acceptor_sulfate.unannotated":0.156966,"electron_acceptor_sulfate.unclassified":0.034784,"electron_acceptor_sulfite.false":0.804901,"electron_acceptor_sulfite.no_majority":0.001414,"electron_acceptor_sulfite.true":0.000178,"electron_acceptor_sulfite.unannotated":0.156966,"electron_acceptor_sulfite.unclassified":0.034784,"electron_acceptor_sulfur_compounds.false":0.799739,"electron_acceptor_sulfur_compounds.no_majority":0.002032,"electron_acceptor_sulfur_compounds.true":0.004722,"electron_acceptor_sulfur_compounds.unannotated":0.156966,"electron_acceptor_sulfur_compounds.unclassified":0.034784,"electron_acceptor_thiosulfate.false":0.800618,"electron_acceptor_thiosulfate.no_majority":0.002841,"electron_acceptor_thiosulfate.true":0.003034,"electron_acceptor_thiosulfate.unannotated":0.156966,"electron_acceptor_thiosulfate.unclassified":0.034784,"energy_source_cellobiose.false":0.000316,"energy_source_cellobiose.true":0.026905,"energy_source_cellobiose.unannotated":0.936239,"energy_source_cellobiose.unclassified":0.034784,"enzyme_activity_acid_phosphatase_ec3_1_3_2.false":0.010515,"enzyme_activity_acid_phosphatase_ec3_1_3_2.no_majority":0.080645,"enzyme_activity_acid_phosphatase_ec3_1_3_2.true":0.365106,"enzyme_activity_acid_phosphatase_ec3_1_3_2.unannotated":0.507193,"enzyme_activity_acid_phosphatase_ec3_1_3_2.unclassified":0.034784,"enzyme_activity_agarase_ec3_2_1_81.false":0.010048,"enzyme_activity_agarase_ec3_2_1_81.true":0.000178,"enzyme_activity_agarase_ec3_2_1_81.unannotated":0.953233,"enzyme_activity_agarase_ec3_2_1_81.unclassified":0.034784,"enzyme_activity_alkaline_phosphatase_ec3_1_3_1.false":0.093246,"enzyme_activity_alkaline_phosphatase_ec3_1_3_1.no_majority":0.213754,"enzyme_activity_alkaline_phosphatase_ec3_1_3_1.true":0.565216,"enzyme_activity_alkaline_phosphatase_ec3_1_3_1.unannotated":0.091242,"enzyme_activity_alkaline_phosphatase_ec3_1_3_1.unclassified":0.034784,"enzyme_activity_amylase.false":0.032258,"enzyme_activity_amylase.no_majority":0.123102,"enzyme_activity_amylase.true":0.046507,"enzyme_activity_amylase.unannotated":0.761592,"enzyme_activity_amylase.unclassified":0.034784,"enzyme_activity_caseinase_ec3_4_21_50.false":0.029101,"enzyme_activity_caseinase_ec3_4_21_50.no_majority":0.041702,"enzyme_activity_caseinase_ec3_4_21_50.true":0.002828,"enzyme_activity_caseinase_ec3_4_21_50.unannotated":0.889829,"enzyme_activity_caseinase_ec3_4_21_50.unclassified":0.034784,"enzyme_activity_cellulase_ec3_2_1_4.false":0.002471,"enzyme_activity_cellulase_ec3_2_1_4.true":0.029897,"enzyme_activity_cellulase_ec3_2_1_4.unannotated":0.931091,"enzyme_activity_cellulase_ec3_2_1_4.unclassified":0.034784,"enzyme_activity_chitinase_ec3_2_1_14.false":0.000137,"enzyme_activity_chitinase_ec3_2_1_14.true":0.022581,"enzyme_activity_chitinase_ec3_2_1_14.unannotated":0.940741,"enzyme_activity_chitinase_ec3_2_1_14.unclassified":0.034784,"enzyme_activity_esterase.false":0.000329,"enzyme_activity_esterase.true":0.047344,"enzyme_activity_esterase.unannotated":0.915786,"enzyme_activity_esterase.unclassified":0.034784,"enzyme_activity_esterase_c_4.false":0.0028,"enzyme_activity_esterase_c_4.no_majority":0.044749,"enzyme_activity_esterase_c_4.true":0.114372,"enzyme_activity_esterase_c_4.unannotated":0.801538,"enzyme_activity_esterase_c_4.unclassified":0.034784,"enzyme_activity_esterase_lipase_c_8.false":0.004653,"enzyme_activity_esterase_lipase_c_8.no_majority":0.015745,"enzyme_activity_esterase_lipase_c_8.true":0.035402,"enzyme_activity_esterase_lipase_c_8.unannotated":0.90766,"enzyme_activity_esterase_lipase_c_8.unclassified":0.034784,"enzyme_activity_gelatinase.false":0.050446,"enzyme_activity_gelatinase.no_majority":0.07326,"enzyme_activity_gelatinase.true":0.073137,"enzyme_activity_gelatinase.unannotated":0.766616,"enzyme_activity_gelatinase.unclassified":0.034784,"enzyme_activity_lipase.false":0.108799,"enzyme_activity_lipase.no_majority":0.285079,"enzyme_activity_lipase.true":0.369485,"enzyme_activity_lipase.unannotated":0.200096,"enzyme_activity_lipase.unclassified":0.034784,"enzyme_activity_lipase_c_14.false":0.027865,"enzyme_activity_lipase_c_14.no_majority":0.023075,"enzyme_activity_lipase_c_14.true":0.024063,"enzyme_activity_lipase_c_14.unannotated":0.888456,"enzyme_activity_lipase_c_14.unclassified":0.034784,"enzyme_activity_naphthol_as_bi_phosphohydrolase.false":0.002718,"enzyme_activity_naphthol_as_bi_phosphohydrolase.true":0.087467,"enzyme_activity_naphthol_as_bi_phosphohydrolase.unannotated":0.873274,"enzyme_activity_naphthol_as_bi_phosphohydrolase.unclassified":0.034784,"enzyme_activity_nitrate_reductase_ec1_7_99_4.false":0.0014,"enzyme_activity_nitrate_reductase_ec1_7_99_4.no_majority":0.000206,"enzyme_activity_nitrate_reductase_ec1_7_99_4.true":0.009911,"enzyme_activity_nitrate_reductase_ec1_7_99_4.unannotated":0.951942,"enzyme_activity_nitrate_reductase_ec1_7_99_4.unclassified":0.034784,"enzyme_activity_phosphatase.true":0.005491,"enzyme_activity_phosphatase.unannotated":0.957969,"enzyme_activity_phosphatase.unclassified":0.034784,"enzyme_activity_protease.false":0.000673,"enzyme_activity_protease.unannotated":0.962787,"enzyme_activity_protease.unclassified":0.034784,"enzyme_activity_ribulose_bisphosphate_carboxylase_ec4_1_1_39.false":0.000453,"enzyme_activity_ribulose_bisphosphate_carboxylase_ec4_1_1_39.unannotated":0.963006,"enzyme_activity_ribulose_bisphosphate_carboxylase_ec4_1_1_39.unclassified":0.034784,"enzyme_activity_tween_esterase.false":0.000151,"enzyme_activity_tween_esterase.true":0.000796,"enzyme_activity_tween_esterase.unannotated":0.962512,"enzyme_activity_tween_esterase.unclassified":0.034784,"enzyme_activity_urease_ec3_5_1_5.false":0.082924,"enzyme_activity_urease_ec3_5_1_5.no_majority":0.114276,"enzyme_activity_urease_ec3_5_1_5.true":0.04884,"enzyme_activity_urease_ec3_5_1_5.unannotated":0.717419,"enzyme_activity_urease_ec3_5_1_5.unclassified":0.034784,"facultative_anaerobe.false":0.719204,"facultative_anaerobe.no_majority":0.037598,"facultative_anaerobe.true":0.006561,"facultative_anaerobe.unannotated":0.200096,"facultative_anaerobe.unclassified":0.034784,"fermentation.false":0.773013,"fermentation.no_majority":0.023075,"fermentation.true":0.010405,"fermentation.unannotated":0.156966,"fermentation.unclassified":0.034784,"fermentation_cellobiose.false":0.079492,"fermentation_cellobiose.no_majority":0.000398,"fermentation_cellobiose.true":0.002457,"fermentation_cellobiose.unannotated":0.881112,"fermentation_cellobiose.unclassified":0.034784,"fermentation_cellulose.false":0.022402,"fermentation_cellulose.true":0.001839,"fermentation_cellulose.unannotated":0.939218,"fermentation_cellulose.unclassified":0.034784,"fermentation_gelatin.false":0.022402,"fermentation_gelatin.unannotated":0.941057,"fermentation_gelatin.unclassified":0.034784,"fermentation_glycogen.false":0.092409,"fermentation_glycogen.no_majority":0.014317,"fermentation_glycogen.true":0.002237,"fermentation_glycogen.unannotated":0.854496,"fermentation_glycogen.unclassified":0.034784,"fermentation_inuline.false":0.009911,"fermentation_inuline.unannotated":0.953548,"fermentation_inuline.unclassified":0.034784,"growth_42_degrees_celsius.false":0.063281,"growth_42_degrees_celsius.no_majority":0.217021,"growth_42_degrees_celsius.true":0.483061,"growth_42_degrees_celsius.unannotated":0.200096,"growth_42_degrees_celsius.unclassified":0.034784,"growth_6_5_nacl.false":0.239025,"growth_6_5_nacl.no_majority":0.248579,"growth_6_5_nacl.true":0.275758,"growth_6_5_nacl.unannotated":0.200096,"growth_6_5_nacl.unclassified":0.034784,"growth_agarose.false":0.000288,"growth_agarose.unannotated":0.963171,"growth_agarose.unclassified":0.034784,"growth_anoxygenic_photoautotrophy.false":0.780728,"growth_anoxygenic_photoautotrophy.no_majority":0.024447,"growth_anoxygenic_photoautotrophy.true":0.001318,"growth_anoxygenic_photoautotrophy.unannotated":0.156966,"growth_anoxygenic_photoautotrophy.unclassified":0.034784,"growth_arabinan.true":0.001167,"growth_arabinan.unannotated":0.962292,"growth_arabinan.unclassified":0.034784,"growth_arabinogalactan.false":0.001167,"growth_arabinogalactan.unannotated":0.962292,"growth_arabinogalactan.unclassified":0.034784,"growth_carboxymethylcellulose.false":0.000398,"growth_carboxymethylcellulose.true":0.001455,"growth_carboxymethylcellulose.unannotated":0.961606,"growth_carboxymethylcellulose.unclassified":0.034784,"growth_casein_hydrolysate.true":0.000316,"growth_casein_hydrolysate.unannotated":0.963144,"growth_casein_hydrolysate.unclassified":0.034784,"growth_cellobiose.false":0.211064,"growth_cellobiose.no_majority":0.380343,"growth_cellobiose.true":0.172807,"growth_cellobiose.unannotated":0.199245,"growth_cellobiose.unclassified":0.034784,"growth_cellulose.false":0.040329,"growth_cellulose.no_majority":0.034468,"growth_cellulose.true":0.008387,"growth_cellulose.unannotated":0.880275,"growth_cellulose.unclassified":0.034784,"growth_chemoheterotrophy.false":0.078723,"growth_chemoheterotrophy.no_majority":0.016362,"growth_chemoheterotrophy.true":0.711407,"growth_chemoheterotrophy.unannotated":0.156966,"growth_chemoheterotrophy.unclassified":0.034784,"growth_chitin.false":0.000714,"growth_chitin.true":0.000288,"growth_chitin.unannotated":0.962457,"growth_chitin.unclassified":0.034784,"growth_macconkey_agar.false":0.534194,"growth_macconkey_agar.no_majority":0.010748,"growth_macconkey_agar.true":0.218421,"growth_macconkey_agar.unannotated":0.200096,"growth_macconkey_agar.unclassified":0.034784,"growth_photoautotrophy.false":0.779959,"growth_photoautotrophy.no_majority":0.024722,"growth_photoautotrophy.true":0.001812,"growth_photoautotrophy.unannotated":0.156966,"growth_photoautotrophy.unclassified":0.034784,"growth_photoheterotrophy.false":0.733727,"growth_photoheterotrophy.no_majority":0.063761,"growth_photoheterotrophy.true":0.009005,"growth_photoheterotrophy.unannotated":0.156966,"growth_photoheterotrophy.unclassified":0.034784,"growth_phototrophy.false":0.730089,"growth_phototrophy.no_majority":0.064887,"growth_phototrophy.true":0.011517,"growth_phototrophy.unannotated":0.156966,"growth_phototrophy.unclassified":0.034784,"hydrolysis_agar.false":0.016637,"hydrolysis_agar.no_majority":0.000178,"hydrolysis_agar.unannotated":0.946644,"hydrolysis_agar.unclassified":0.034784,"hydrolysis_alginate.false":0.005504,"hydrolysis_alginate.true":0.000933,"hydrolysis_alginate.unannotated":0.957021,"hydrolysis_alginate.unclassified":0.034784,"hydrolysis_carboxymethylcellulose.false":0.073191,"hydrolysis_carboxymethylcellulose.no_majority":0.091393,"hydrolysis_carboxymethylcellulose.true":0.006795,"hydrolysis_carboxymethylcellulose.unannotated":0.79208,"hydrolysis_carboxymethylcellulose.unclassified":0.034784,"hydrolysis_casein.false":0.266246,"hydrolysis_casein.no_majority":0.308456,"hydrolysis_casein.true":0.191654,"hydrolysis_casein.unannotated":0.197104,"hydrolysis_casein.unclassified":0.034784,"hydrolysis_cationic_chitosan.false":0.000398,"hydrolysis_cationic_chitosan.unannotated":0.963061,"hydrolysis_cationic_chitosan.unclassified":0.034784,"hydrolysis_cellulose.false":0.061647,"hydrolysis_cellulose.no_majority":0.052903,"hydrolysis_cellulose.true":0.039574,"hydrolysis_cellulose.unannotated":0.809334,"hydrolysis_cellulose.unclassified":0.034784,"hydrolysis_chitin.false":0.121771,"hydrolysis_chitin.no_majority":0.030268,"hydrolysis_chitin.unannotated":0.811421,"hydrolysis_chitin.unclassified":0.034784,"hydrolysis_crab_shell_chitin.false":0.006452,"hydrolysis_crab_shell_chitin.unannotated":0.957008,"hydrolysis_crab_shell_chitin.unclassified":0.034784,"hydrolysis_crystalline_cellulose.false":0.001894,"hydrolysis_crystalline_cellulose.unannotated":0.961565,"hydrolysis_crystalline_cellulose.unclassified":0.034784,"hydrolysis_dna.false":0.046136,"hydrolysis_dna.no_majority":0.020082,"hydrolysis_dna.true":0.005518,"hydrolysis_dna.unannotated":0.891723,"hydrolysis_dna.unclassified":0.034784,"hydrolysis_gelatin.false":0.136019,"hydrolysis_gelatin.no_majority":0.267303,"hydrolysis_gelatin.true":0.370995,"hydrolysis_gelatin.unannotated":0.189142,"hydrolysis_gelatin.unclassified":0.034784,"hydrolysis_skimmed_milk.true":0.003294,"hydrolysis_skimmed_milk.unannotated":0.960165,"hydrolysis_skimmed_milk.unclassified":0.034784,"hydrolysis_starch.false":0.262498,"hydrolysis_starch.no_majority":0.324626,"hydrolysis_starch.true":0.176239,"hydrolysis_starch.unannotated":0.200096,"hydrolysis_starch.unclassified":0.034784,"hydrolysis_tween_20.false":0.027879,"hydrolysis_tween_20.unannotated":0.93558,"hydrolysis_tween_20.unclassified":0.034784,"hydrolysis_tween_40.false":0.029664,"hydrolysis_tween_40.unannotated":0.933796,"hydrolysis_tween_40.unclassified":0.034784,"hydrolysis_tween_60.false":0.004914,"hydrolysis_tween_60.true":0.024749,"hydrolysis_tween_60.unannotated":0.933796,"hydrolysis_tween_60.unclassified":0.034784,"hydrolysis_tween_80.false":0.000151,"hydrolysis_tween_80.true":0.022402,"hydrolysis_tween_80.unannotated":0.940906,"hydrolysis_tween_80.unclassified":0.034784,"hydrolysis_urea.false":0.3986,"hydrolysis_urea.no_majority":0.410075,"hydrolysis_urea.true":0.001112,"hydrolysis_urea.unannotated":0.153672,"hydrolysis_urea.unclassified":0.034784,"hydrolysis_xylan.false":0.805875,"hydrolysis_xylan.no_majority":0.000618,"hydrolysis_xylan.unannotated":0.156966,"hydrolysis_xylan.unclassified":0.034784,"nitrification.false":0.745079,"nitrification.no_majority":0.000879,"nitrification.true":0.060535,"nitrification.unannotated":0.156966,"nitrification.unclassified":0.034784,"nitrogen_fixation.false":0.762745,"nitrogen_fixation.no_majority":0.032931,"nitrogen_fixation.true":0.010817,"nitrogen_fixation.unannotated":0.156966,"nitrogen_fixation.unclassified":0.034784,"nitrogen_source_ammonium.true":0.034949,"nitrogen_source_ammonium.unannotated":0.928511,"nitrogen_source_ammonium.unclassified":0.034784,"nitrogen_source_ammonium_chloride.true":0.000288,"nitrogen_source_ammonium_chloride.unannotated":0.963171,"nitrogen_source_ammonium_chloride.unclassified":0.034784,"nitrogen_source_ammonium_sulfate.true":0.02372,"nitrogen_source_ammonium_sulfate.unannotated":0.939739,"nitrogen_source_ammonium_sulfate.unclassified":0.034784,"obligate_aerobic.false":0.030076,"obligate_aerobic.no_majority":0.152258,"obligate_aerobic.true":0.627454,"obligate_aerobic.unannotated":0.153672,"obligate_aerobic.unclassified":0.034784,"obligate_anaerobic.false":0.602128,"obligate_anaerobic.no_majority":0.187907,"obligate_anaerobic.true":0.019753,"obligate_anaerobic.unannotated":0.153672,"obligate_anaerobic.unclassified":0.034784,"oxidation_alpha_cyclodextrin.true":0.000618,"oxidation_alpha_cyclodextrin.unannotated":0.962842,"oxidation_alpha_cyclodextrin.unclassified":0.034784,"oxidation_ammonia.false":0.742553,"oxidation_ammonia.no_majority":0.011736,"oxidation_ammonia.true":0.052203,"oxidation_ammonia.unannotated":0.156966,"oxidation_ammonia.unclassified":0.034784,"oxidation_cellobiose.true":0.011627,"oxidation_cellobiose.unannotated":0.951833,"oxidation_cellobiose.unclassified":0.034784,"oxidation_dextrin.no_majority":0.001153,"oxidation_dextrin.unannotated":0.962306,"oxidation_dextrin.unclassified":0.034784,"oxidation_elemental_sulfur.false":0.000494,"oxidation_elemental_sulfur.true":0.000851,"oxidation_elemental_sulfur.unannotated":0.962114,"oxidation_elemental_sulfur.unclassified":0.034784,"oxidation_in_darkness_iron.false":0.799492,"oxidation_in_darkness_iron.no_majority":0.007001,"oxidation_in_darkness_iron.unannotated":0.156966,"oxidation_in_darkness_iron.unclassified":0.034784,"oxidation_in_darkness_sulfide.false":0.798957,"oxidation_in_darkness_sulfide.no_majority":0.007536,"oxidation_in_darkness_sulfide.unannotated":0.156966,"oxidation_in_darkness_sulfide.unclassified":0.034784,"oxidation_in_darkness_sulfur_compounds.false":0.767646,"oxidation_in_darkness_sulfur_compounds.no_majority":0.032587,"oxidation_in_darkness_sulfur_compounds.true":0.006259,"oxidation_in_darkness_sulfur_compounds.unannotated":0.156966,"oxidation_in_darkness_sulfur_compounds.unclassified":0.034784,"oxidation_iron.true":0.000494,"oxidation_iron.unannotated":0.962965,"oxidation_iron.unclassified":0.034784,"oxidation_methanol.false":0.799739,"oxidation_methanol.no_majority":0.006754,"oxidation_methanol.unannotated":0.156966,"oxidation_methanol.unclassified":0.034784,"oxidation_pyrite.true":0.000494,"oxidation_pyrite.unannotated":0.962965,"oxidation_pyrite.unclassified":0.034784,"oxidation_sulfide.true":0.000851,"oxidation_sulfide.unannotated":0.962608,"oxidation_sulfide.unclassified":0.034784,"oxidation_thiosulfate.true":0.000851,"oxidation_thiosulfate.unannotated":0.962608,"oxidation_thiosulfate.unclassified":0.034784,"oxygen_preference.aerobic":0.389334,"oxygen_preference.no_majority":0.28641,"oxygen_preference.other":0.083157,"oxygen_preference.unannotated":0.204557,"oxygen_preference.unclassified":0.034784,"ph_growth.mean":7.143514,"ph_growth.unannotated":0.12766,"ph_growth.unclassified":0.034784,"ph_maximum.mean":9.0384,"ph_maximum.unannotated":0.029856,"ph_maximum.unclassified":0.034784,"ph_minimum.mean":5.329134,"ph_minimum.unannotated":0.029856,"ph_minimum.unclassified":0.034784,"ph_preference.alkaliphile":0.408044,"ph_preference.no_majority":0.015292,"ph_preference.other":0.010625,"ph_preference.unannotated":0.529499,"ph_preference.unclassified":0.034784,"presence_of_motility.false":0.455278,"presence_of_motility.no_majority":0.255607,"presence_of_motility.true":0.202402,"presence_of_motility.unannotated":0.050172,"presence_of_motility.unclassified":0.034784,"produces_cellulose.true":0.024749,"produces_cellulose.unannotated":0.93871,"produces_cellulose.unclassified":0.034784,"produces_dinitrogen.false":0.043487,"produces_dinitrogen.no_majority":0.014317,"produces_dinitrogen.true":0.000563,"produces_dinitrogen.unannotated":0.905093,"produces_dinitrogen.unclassified":0.034784,"produces_exopolysaccharide.true":0.004406,"produces_exopolysaccharide.unannotated":0.959053,"produces_exopolysaccharide.unclassified":0.034784,"produces_hydrogen_sulfide.false":0.562539,"produces_hydrogen_sulfide.no_majority":0.168016,"produces_hydrogen_sulfide.true":0.039039,"produces_hydrogen_sulfide.unannotated":0.193864,"produces_hydrogen_sulfide.unclassified":0.034784,"produces_indole_3_acetate.false":0.021249,"produces_indole_3_acetate.true":0.022402,"produces_indole_3_acetate.unannotated":0.919808,"produces_indole_3_acetate.unclassified":0.034784,"produces_methane.true":0.006452,"produces_methane.unannotated":0.957008,"produces_methane.unclassified":0.034784,"produces_methane_from_acetate.false":0.806493,"produces_methane_from_acetate.unannotated":0.156966,"produces_methane_from_acetate.unclassified":0.034784,"produces_methane_from_formate.false":0.806493,"produces_methane_from_formate.unannotated":0.156966,"produces_methane_from_formate.unclassified":0.034784,"produces_nitrate.false":0.004502,"produces_nitrate.unannotated":0.958957,"produces_nitrate.unclassified":0.034784,"produces_nitrite.false":0.043528,"produces_nitrite.no_majority":0.000618,"produces_nitrite.true":0.010075,"produces_nitrite.unannotated":0.909238,"produces_nitrite.unclassified":0.034784,"produces_phenazines.true":0.000933,"produces_phenazines.unannotated":0.962526,"produces_phenazines.unclassified":0.034784,"produces_polyhydroxybutyrate.false":0.000137,"produces_polyhydroxybutyrate.true":0.032189,"produces_polyhydroxybutyrate.unannotated":0.931133,"produces_polyhydroxybutyrate.unclassified":0.034784,"produces_siderophore.true":0.004406,"produces_siderophore.unannotated":0.959053,"produces_siderophore.unclassified":0.034784,"psychrophilic.false":0.806493,"psychrophilic.unannotated":0.156966,"psychrophilic.unclassified":0.034784,"reduction_nitrate.false":0.298792,"reduction_nitrate.no_majority":0.483542,"reduction_nitrate.true":0.028058,"reduction_nitrate.unannotated":0.153068,"reduction_nitrate.unclassified":0.034784,"reduction_nitrite.false":0.510982,"reduction_nitrite.no_majority":0.194345,"reduction_nitrite.true":0.059629,"reduction_nitrite.unannotated":0.198504,"reduction_nitrite.unclassified":0.034784,"reduction_sulfate.true":0.00022,"reduction_sulfate.unannotated":0.96324,"reduction_sulfate.unclassified":0.034784,"required_for_growth_sodium_chloride.false":0.000343,"required_for_growth_sodium_chloride.unannotated":0.963116,"required_for_growth_sodium_chloride.unclassified":0.034784,"respiration_alpha_cyclodextrin.false":0.000755,"respiration_alpha_cyclodextrin.true":0.002512,"respiration_alpha_cyclodextrin.unannotated":0.960192,"respiration_alpha_cyclodextrin.unclassified":0.034784,"respiration_beta_cyclodextrin.false":0.000755,"respiration_beta_cyclodextrin.unannotated":0.962704,"respiration_beta_cyclodextrin.unclassified":0.034784,"respiration_cellobiose.true":0.004406,"respiration_cellobiose.unannotated":0.959053,"respiration_cellobiose.unclassified":0.034784,"respiration_nitrate.false":0.096706,"respiration_nitrate.no_majority":0.016458,"respiration_nitrate.true":0.015278,"respiration_nitrate.unannotated":0.835017,"respiration_nitrate.unclassified":0.034784,"respiration_nitrogen.false":0.782045,"respiration_nitrogen.no_majority":0.023953,"respiration_nitrogen.true":0.000494,"respiration_nitrogen.unannotated":0.156966,"respiration_nitrogen.unclassified":0.034784,"salinity_growth.mean":1.151678,"salinity_growth.unannotated":0.034674,"salinity_growth.unclassified":0.034784,"salinity_maximum.mean":3.564149,"salinity_maximum.unannotated":0.034001,"salinity_maximum.unclassified":0.034784,"salinity_minimum.mean":0.387131,"salinity_minimum.unannotated":0.062787,"salinity_minimum.unclassified":0.034784,"salinity_preference.no_majority":0.113205,"salinity_preference.non_halophilic":0.039369,"salinity_preference.other":0.063802,"salinity_preference.unannotated":0.747083,"salinity_preference.unclassified":0.034784,"sporulation.false":0.798435,"sporulation.no_majority":0.031407,"sporulation.true":0.07779,"sporulation.unannotated":0.055827,"sporulation.unclassified":0.034784,"temperature_growth.mean":31.77108,"temperature_growth.unannotated":0.01116,"temperature_growth.unclassified":0.034784,"temperature_maximum.mean":40.517283,"temperature_maximum.unannotated":0.029293,"temperature_maximum.unclassified":0.034784,"temperature_minimum.mean":17.566628,"temperature_minimum.unannotated":0.029293,"temperature_minimum.unclassified":0.034784,"temperature_preference.mesophilic":0.287687,"temperature_preference.no_majority":0.025353,"temperature_preference.other":0.027646,"temperature_preference.unannotated":0.622773,"temperature_preference.unclassified":0.034784,"thermophilic.false":0.802759,"thermophilic.no_majority":0.002237,"thermophilic.true":0.001496,"thermophilic.unannotated":0.156966,"thermophilic.unclassified":0.034784,"utilizes_casein.true":0.010185,"utilizes_casein.unannotated":0.953274,"utilizes_casein.unclassified":0.034784,"utilizes_cellobiose.true":0.004406,"utilizes_cellobiose.unannotated":0.959053,"utilizes_cellobiose.unclassified":0.034784,"utilizes_cellulose.false":0.027481,"utilizes_cellulose.no_majority":0.06324,"utilizes_cellulose.true":0.003143,"utilizes_cellulose.unannotated":0.869595,"utilizes_cellulose.unclassified":0.034784,"utilizes_gelatin.false":0.006809,"utilizes_gelatin.true":0.009911,"utilizes_gelatin.unannotated":0.94674,"utilizes_gelatin.unclassified":0.034784}