{"acidophilic.false":0.842527,"acidophilic.unannotated":0.123774,"acidophilic.unclassified":0.028831,"aerobic_growth_anoxygenic_phototrophy.false":0.827086,"aerobic_growth_anoxygenic_phototrophy.no_majority":0.015441,"aerobic_growth_anoxygenic_phototrophy.unannotated":0.123774,"aerobic_growth_anoxygenic_phototrophy.unclassified":0.028831,"aerotolerant.false":0.07868,"aerotolerant.no_majority":0.088154,"aerotolerant.true":0.775428,"aerotolerant.unannotated":0.024039,"aerotolerant.unclassified":0.028831,"ammonification_nitrate.false":0.842527,"ammonification_nitrate.unannotated":0.123774,"ammonification_nitrate.unclassified":0.028831,"ammonification_nitrite.false":0.842527,"ammonification_nitrite.unannotated":0.123774,"ammonification_nitrite.unclassified":0.028831,"assimilation_benzene.false":0.00097,"assimilation_benzene.true":0.010182,"assimilation_benzene.unannotated":0.955149,"assimilation_benzene.unclassified":0.028831,"assimilation_casein.false":0.010182,"assimilation_casein.true":0.004177,"assimilation_casein.unannotated":0.951941,"assimilation_casein.unclassified":0.028831,"assimilation_cellobiose.false":0.015796,"assimilation_cellobiose.no_majority":0.06626,"assimilation_cellobiose.true":0.02029,"assimilation_cellobiose.unannotated":0.863955,"assimilation_cellobiose.unclassified":0.028831,"assimilation_cellulose.false":0.019768,"assimilation_cellulose.no_majority":0.00041,"assimilation_cellulose.unannotated":0.946123,"assimilation_cellulose.unclassified":0.028831,"assimilation_chitin.true":0.010182,"assimilation_chitin.unannotated":0.956119,"assimilation_chitin.unclassified":0.028831,"assimilation_chitosan.true":0.010761,"assimilation_chitosan.unannotated":0.955541,"assimilation_chitosan.unclassified":0.028831,"assimilation_dextrin.true":0.000578,"assimilation_dextrin.unannotated":0.965723,"assimilation_dextrin.unclassified":0.028831,"assimilation_gelatin.false":0.001921,"assimilation_gelatin.no_majority":0.010182,"assimilation_gelatin.true":0.00662,"assimilation_gelatin.unannotated":0.947577,"assimilation_gelatin.unclassified":0.028831,"assimilation_glycogen.true":0.002835,"assimilation_glycogen.unannotated":0.963466,"assimilation_glycogen.unclassified":0.028831,"builds_gas_from_nitrate.false":0.012551,"builds_gas_from_nitrate.unannotated":0.95375,"builds_gas_from_nitrate.unclassified":0.028831,"builds_gas_from_nitrite.false":0.010723,"builds_gas_from_nitrite.unannotated":0.955578,"builds_gas_from_nitrite.unclassified":0.028831,"capnophilic.false":0.590746,"capnophilic.no_majority":0.182332,"capnophilic.true":0.025624,"capnophilic.unannotated":0.167599,"capnophilic.unclassified":0.028831,"carbon_source_alginate.false":0.003972,"carbon_source_alginate.unannotated":0.962329,"carbon_source_alginate.unclassified":0.028831,"carbon_source_alpha_cyclodextrin.true":0.029671,"carbon_source_alpha_cyclodextrin.unannotated":0.93663,"carbon_source_alpha_cyclodextrin.unclassified":0.028831,"carbon_source_cellobiose.false":0.059845,"carbon_source_cellobiose.no_majority":0.007944,"carbon_source_cellobiose.true":0.137052,"carbon_source_cellobiose.unannotated":0.76146,"carbon_source_cellobiose.unclassified":0.028831,"carbon_source_cellulose.false":0.006434,"carbon_source_cellulose.no_majority":0.010182,"carbon_source_cellulose.true":0.015311,"carbon_source_cellulose.unannotated":0.934374,"carbon_source_cellulose.unclassified":0.028831,"carbon_source_chitosan.no_majority":0.010182,"carbon_source_chitosan.unannotated":0.956119,"carbon_source_chitosan.unclassified":0.028831,"carbon_source_dextran.false":0.00097,"carbon_source_dextran.unannotated":0.965331,"carbon_source_dextran.unclassified":0.028831,"carbon_source_dextrin.no_majority":0.002257,"carbon_source_dextrin.true":0.057197,"carbon_source_dextrin.unannotated":0.906848,"carbon_source_dextrin.unclassified":0.028831,"carbon_source_gelatin.true":0.054866,"carbon_source_gelatin.unannotated":0.911436,"carbon_source_gelatin.unclassified":0.028831,"carbon_source_glycogen.true":0.059155,"carbon_source_glycogen.unannotated":0.907146,"carbon_source_glycogen.unclassified":0.028831,"carbon_source_starch.false":0.010182,"carbon_source_starch.unannotated":0.956119,"carbon_source_starch.unclassified":0.028831,"degradation_agar.false":0.001082,"degradation_agar.unannotated":0.965219,"degradation_agar.unclassified":0.028831,"degradation_alginate.true":0.016448,"degradation_alginate.unannotated":0.949853,"degradation_alginate.unclassified":0.028831,"degradation_aromatic_compound.false":0.840028,"degradation_aromatic_compound.no_majority":0.002499,"degradation_aromatic_compound.unannotated":0.123774,"degradation_aromatic_compound.unclassified":0.028831,"degradation_aromatic_hydrocarbon.false":0.840457,"degradation_aromatic_hydrocarbon.no_majority":0.00207,"degradation_aromatic_hydrocarbon.unannotated":0.123774,"degradation_aromatic_hydrocarbon.unclassified":0.028831,"degradation_benzoate.false":0.004177,"degradation_benzoate.unannotated":0.962124,"degradation_benzoate.unclassified":0.028831,"degradation_carboxymethylcellulose.false":0.014155,"degradation_carboxymethylcellulose.true":0.018742,"degradation_carboxymethylcellulose.unannotated":0.933404,"degradation_carboxymethylcellulose.unclassified":0.028831,"degradation_casein.false":0.006509,"degradation_casein.no_majority":0.011562,"degradation_casein.true":0.00815,"degradation_casein.unannotated":0.940081,"degradation_casein.unclassified":0.028831,"degradation_cellobiose.false":0.034426,"degradation_cellobiose.no_majority":0.006229,"degradation_cellobiose.true":0.002294,"degradation_cellobiose.unannotated":0.923352,"degradation_cellobiose.unclassified":0.028831,"degradation_cellulose.false":0.81377,"degradation_cellulose.no_majority":0.029242,"degradation_cellulose.true":0.000597,"degradation_cellulose.unannotated":0.122692,"degradation_cellulose.unclassified":0.028831,"degradation_chitin.false":0.772146,"degradation_chitin.no_majority":0.071183,"degradation_chitin.unannotated":0.122972,"degradation_chitin.unclassified":0.028831,"degradation_chitosan.false":0.001846,"degradation_chitosan.unannotated":0.964455,"degradation_chitosan.unclassified":0.028831,"degradation_dna.true":0.001846,"degradation_dna.unannotated":0.964455,"degradation_dna.unclassified":0.028831,"degradation_gelatin.false":0.004588,"degradation_gelatin.no_majority":0.010182,"degradation_gelatin.true":0.010723,"degradation_gelatin.unannotated":0.940808,"degradation_gelatin.unclassified":0.028831,"degradation_hydrocarbon.false":0.839189,"degradation_hydrocarbon.no_majority":0.003338,"degradation_hydrocarbon.unannotated":0.123774,"degradation_hydrocarbon.unclassified":0.028831,"degradation_lignin.false":0.838369,"degradation_lignin.no_majority":0.004159,"degradation_lignin.unannotated":0.123774,"degradation_lignin.unclassified":0.028831,"degradation_phenol.false":0.000224,"degradation_phenol.true":0.000317,"degradation_phenol.unannotated":0.96576,"degradation_phenol.unclassified":0.028831,"degradation_plastic.false":0.788072,"degradation_plastic.no_majority":0.054455,"degradation_plastic.unannotated":0.123774,"degradation_plastic.unclassified":0.028831,"degradation_skimmed_milk.true":0.010182,"degradation_skimmed_milk.unannotated":0.956119,"degradation_skimmed_milk.unclassified":0.028831,"denitrification_nitrate.false":0.700888,"denitrification_nitrate.no_majority":0.013894,"denitrification_nitrate.true":0.127746,"denitrification_nitrate.unannotated":0.123774,"denitrification_nitrate.unclassified":0.028831,"denitrification_nitrite.false":0.715937,"denitrification_nitrite.no_majority":0.114076,"denitrification_nitrite.true":0.012514,"denitrification_nitrite.unannotated":0.123774,"denitrification_nitrite.unclassified":0.028831,"denitrification_nitrous_oxide.false":0.703666,"denitrification_nitrous_oxide.no_majority":0.067435,"denitrification_nitrous_oxide.true":0.071426,"denitrification_nitrous_oxide.unannotated":0.123774,"denitrification_nitrous_oxide.unclassified":0.028831,"denitrification_pathway.false":0.714408,"denitrification_pathway.no_majority":0.128119,"denitrification_pathway.unannotated":0.123774,"denitrification_pathway.unclassified":0.028831,"electron_acceptor_elemental_sulfur.false":0.811477,"electron_acceptor_elemental_sulfur.no_majority":0.000317,"electron_acceptor_elemental_sulfur.true":0.03299,"electron_acceptor_elemental_sulfur.unannotated":0.121517,"electron_acceptor_elemental_sulfur.unclassified":0.028831,"electron_acceptor_manganese.false":0.83848,"electron_acceptor_manganese.no_majority":0.001473,"electron_acceptor_manganese.true":0.002574,"electron_acceptor_manganese.unannotated":0.123774,"electron_acceptor_manganese.unclassified":0.028831,"electron_acceptor_sulfate.false":0.834844,"electron_acceptor_sulfate.no_majority":0.005483,"electron_acceptor_sulfate.true":0.002201,"electron_acceptor_sulfate.unannotated":0.123774,"electron_acceptor_sulfate.unclassified":0.028831,"electron_acceptor_sulfite.false":0.840998,"electron_acceptor_sulfite.no_majority":0.000765,"electron_acceptor_sulfite.true":0.000765,"electron_acceptor_sulfite.unannotated":0.123774,"electron_acceptor_sulfite.unclassified":0.028831,"electron_acceptor_sulfur_compounds.false":0.803178,"electron_acceptor_sulfur_compounds.no_majority":0.006136,"electron_acceptor_sulfur_compounds.true":0.033214,"electron_acceptor_sulfur_compounds.unannotated":0.123774,"electron_acceptor_sulfur_compounds.unclassified":0.028831,"electron_acceptor_thiosulfate.false":0.837473,"electron_acceptor_thiosulfate.no_majority":0.004867,"electron_acceptor_thiosulfate.true":0.000186,"electron_acceptor_thiosulfate.unannotated":0.123774,"electron_acceptor_thiosulfate.unclassified":0.028831,"energy_source_cellobiose.no_majority":0.00041,"energy_source_cellobiose.true":0.021372,"energy_source_cellobiose.unannotated":0.944519,"energy_source_cellobiose.unclassified":0.028831,"enzyme_activity_acid_phosphatase_ec3_1_3_2.false":0.01602,"enzyme_activity_acid_phosphatase_ec3_1_3_2.no_majority":0.200683,"enzyme_activity_acid_phosphatase_ec3_1_3_2.true":0.182985,"enzyme_activity_acid_phosphatase_ec3_1_3_2.unannotated":0.566614,"enzyme_activity_acid_phosphatase_ec3_1_3_2.unclassified":0.028831,"enzyme_activity_agarase_ec3_2_1_81.false":0.003972,"enzyme_activity_agarase_ec3_2_1_81.true":0.000317,"enzyme_activity_agarase_ec3_2_1_81.unannotated":0.962012,"enzyme_activity_agarase_ec3_2_1_81.unclassified":0.028831,"enzyme_activity_alkaline_phosphatase_ec3_1_3_1.false":0.105218,"enzyme_activity_alkaline_phosphatase_ec3_1_3_1.no_majority":0.332382,"enzyme_activity_alkaline_phosphatase_ec3_1_3_1.true":0.481146,"enzyme_activity_alkaline_phosphatase_ec3_1_3_1.unannotated":0.047555,"enzyme_activity_alkaline_phosphatase_ec3_1_3_1.unclassified":0.028831,"enzyme_activity_amylase.false":0.122636,"enzyme_activity_amylase.no_majority":0.064395,"enzyme_activity_amylase.true":0.002275,"enzyme_activity_amylase.unannotated":0.776994,"enzyme_activity_amylase.unclassified":0.028831,"enzyme_activity_caseinase_ec3_4_21_50.false":0.004681,"enzyme_activity_caseinase_ec3_4_21_50.no_majority":0.03133,"enzyme_activity_caseinase_ec3_4_21_50.unannotated":0.93029,"enzyme_activity_caseinase_ec3_4_21_50.unclassified":0.028831,"enzyme_activity_catalase_ec1_11_1_6.false":0.047853,"enzyme_activity_catalase_ec1_11_1_6.no_majority":0.073104,"enzyme_activity_catalase_ec1_11_1_6.true":0.700421,"enzyme_activity_catalase_ec1_11_1_6.unannotated":0.144922,"enzyme_activity_catalase_ec1_11_1_6.unclassified":0.028831,"enzyme_activity_cellulase_ec3_2_1_4.true":0.030771,"enzyme_activity_cellulase_ec3_2_1_4.unannotated":0.93553,"enzyme_activity_cellulase_ec3_2_1_4.unclassified":0.028831,"enzyme_activity_chitinase_ec3_2_1_14.true":0.010499,"enzyme_activity_chitinase_ec3_2_1_14.unannotated":0.955802,"enzyme_activity_chitinase_ec3_2_1_14.unclassified":0.028831,"enzyme_activity_esterase.false":0.002257,"enzyme_activity_esterase.true":0.029391,"enzyme_activity_esterase.unannotated":0.934654,"enzyme_activity_esterase.unclassified":0.028831,"enzyme_activity_esterase_c_4.false":0.000914,"enzyme_activity_esterase_c_4.no_majority":0.021465,"enzyme_activity_esterase_c_4.true":0.075044,"enzyme_activity_esterase_c_4.unannotated":0.868878,"enzyme_activity_esterase_c_4.unclassified":0.028831,"enzyme_activity_esterase_lipase_c_8.false":0.04073,"enzyme_activity_esterase_lipase_c_8.no_majority":0.002163,"enzyme_activity_esterase_lipase_c_8.true":0.017511,"enzyme_activity_esterase_lipase_c_8.unannotated":0.905897,"enzyme_activity_esterase_lipase_c_8.unclassified":0.028831,"enzyme_activity_gelatinase.false":0.075603,"enzyme_activity_gelatinase.no_majority":0.058539,"enzyme_activity_gelatinase.true":0.044776,"enzyme_activity_gelatinase.unannotated":0.787382,"enzyme_activity_gelatinase.unclassified":0.028831,"enzyme_activity_lipase.false":0.155925,"enzyme_activity_lipase.no_majority":0.388646,"enzyme_activity_lipase.true":0.254131,"enzyme_activity_lipase.unannotated":0.167599,"enzyme_activity_lipase.unclassified":0.028831,"enzyme_activity_lipase_c_14.false":0.012066,"enzyme_activity_lipase_c_14.no_majority":0.010182,"enzyme_activity_lipase_c_14.true":0.004084,"enzyme_activity_lipase_c_14.unannotated":0.939969,"enzyme_activity_lipase_c_14.unclassified":0.028831,"enzyme_activity_naphthol_as_bi_phosphohydrolase.false":0.002835,"enzyme_activity_naphthol_as_bi_phosphohydrolase.no_majority":0.002294,"enzyme_activity_naphthol_as_bi_phosphohydrolase.true":0.054008,"enzyme_activity_naphthol_as_bi_phosphohydrolase.unannotated":0.907165,"enzyme_activity_naphthol_as_bi_phosphohydrolase.unclassified":0.028831,"enzyme_activity_nitrate_reductase_ec1_7_99_4.false":0.000783,"enzyme_activity_nitrate_reductase_ec1_7_99_4.no_majority":0.000709,"enzyme_activity_nitrate_reductase_ec1_7_99_4.true":0.084797,"enzyme_activity_nitrate_reductase_ec1_7_99_4.unannotated":0.880012,"enzyme_activity_nitrate_reductase_ec1_7_99_4.unclassified":0.028831,"enzyme_activity_oxidase.false":0.073142,"enzyme_activity_oxidase.no_majority":0.294637,"enzyme_activity_oxidase.true":0.430924,"enzyme_activity_oxidase.unannotated":0.167599,"enzyme_activity_oxidase.unclassified":0.028831,"enzyme_activity_protease.false":0.003077,"enzyme_activity_protease.unannotated":0.963224,"enzyme_activity_protease.unclassified":0.028831,"enzyme_activity_tween_esterase.false":0.000709,"enzyme_activity_tween_esterase.true":0.000317,"enzyme_activity_tween_esterase.unannotated":0.965275,"enzyme_activity_tween_esterase.unclassified":0.028831,"enzyme_activity_urease_ec3_5_1_5.false":0.058968,"enzyme_activity_urease_ec3_5_1_5.no_majority":0.126963,"enzyme_activity_urease_ec3_5_1_5.true":0.038939,"enzyme_activity_urease_ec3_5_1_5.unannotated":0.741431,"enzyme_activity_urease_ec3_5_1_5.unclassified":0.028831,"facultative_anaerobe.false":0.677017,"facultative_anaerobe.no_majority":0.113013,"facultative_anaerobe.true":0.008672,"facultative_anaerobe.unannotated":0.167599,"facultative_anaerobe.unclassified":0.028831,"fermentation.false":0.817146,"fermentation.no_majority":0.006676,"fermentation.true":0.018705,"fermentation.unannotated":0.123774,"fermentation.unclassified":0.028831,"fermentation_cellobiose.false":0.067174,"fermentation_cellobiose.no_majority":0.001249,"fermentation_cellobiose.true":0.006229,"fermentation_cellobiose.unannotated":0.891649,"fermentation_cellobiose.unclassified":0.028831,"fermentation_cellulose.false":0.010649,"fermentation_cellulose.true":0.006229,"fermentation_cellulose.unannotated":0.949424,"fermentation_cellulose.unclassified":0.028831,"fermentation_gelatin.false":0.010182,"fermentation_gelatin.unannotated":0.956119,"fermentation_gelatin.unclassified":0.028831,"fermentation_glycogen.false":0.02857,"fermentation_glycogen.no_majority":0.020421,"fermentation_glycogen.true":0.007012,"fermentation_glycogen.unannotated":0.910298,"fermentation_glycogen.unclassified":0.028831,"fermentation_inuline.false":0.003972,"fermentation_inuline.unannotated":0.962329,"fermentation_inuline.unclassified":0.028831,"growth_42_degrees_celsius.false":0.067267,"growth_42_degrees_celsius.no_majority":0.400134,"growth_42_degrees_celsius.true":0.331301,"growth_42_degrees_celsius.unannotated":0.167599,"growth_42_degrees_celsius.unclassified":0.028831,"growth_6_5_nacl.false":0.329044,"growth_6_5_nacl.no_majority":0.181343,"growth_6_5_nacl.true":0.288314,"growth_6_5_nacl.unannotated":0.167599,"growth_6_5_nacl.unclassified":0.028831,"growth_anoxygenic_photoautotrophy.false":0.783261,"growth_anoxygenic_photoautotrophy.no_majority":0.057327,"growth_anoxygenic_photoautotrophy.true":0.00194,"growth_anoxygenic_photoautotrophy.unannotated":0.123774,"growth_anoxygenic_photoautotrophy.unclassified":0.028831,"growth_cellobiose.false":0.287513,"growth_cellobiose.no_majority":0.357353,"growth_cellobiose.true":0.154358,"growth_cellobiose.unannotated":0.167077,"growth_cellobiose.unclassified":0.028831,"growth_cellulose.false":0.008858,"growth_cellulose.no_majority":0.015926,"growth_cellulose.true":0.002294,"growth_cellulose.unannotated":0.939223,"growth_cellulose.unclassified":0.028831,"growth_chemoheterotrophy.false":0.083809,"growth_chemoheterotrophy.no_majority":0.023722,"growth_chemoheterotrophy.true":0.734997,"growth_chemoheterotrophy.unannotated":0.123774,"growth_chemoheterotrophy.unclassified":0.028831,"growth_macconkey_agar.false":0.584294,"growth_macconkey_agar.no_majority":0.012252,"growth_macconkey_agar.true":0.202156,"growth_macconkey_agar.unannotated":0.167599,"growth_macconkey_agar.unclassified":0.028831,"growth_photoautotrophy.false":0.78065,"growth_photoautotrophy.no_majority":0.059453,"growth_photoautotrophy.true":0.002424,"growth_photoautotrophy.unannotated":0.123774,"growth_photoautotrophy.unclassified":0.028831,"growth_photoheterotrophy.false":0.783167,"growth_photoheterotrophy.no_majority":0.058875,"growth_photoheterotrophy.true":0.000485,"growth_photoheterotrophy.unannotated":0.123774,"growth_photoheterotrophy.unclassified":0.028831,"growth_phototrophy.false":0.781023,"growth_phototrophy.no_majority":0.059229,"growth_phototrophy.true":0.002275,"growth_phototrophy.unannotated":0.123774,"growth_phototrophy.unclassified":0.028831,"growth_starch.false":0.002294,"growth_starch.true":0.00028,"growth_starch.unannotated":0.963728,"growth_starch.unclassified":0.028831,"hydrolysis_agar.false":0.020421,"hydrolysis_agar.no_majority":0.000317,"hydrolysis_agar.unannotated":0.945563,"hydrolysis_agar.unclassified":0.028831,"hydrolysis_alginate.false":0.022062,"hydrolysis_alginate.unannotated":0.944239,"hydrolysis_alginate.unclassified":0.028831,"hydrolysis_carboxymethylcellulose.false":0.020458,"hydrolysis_carboxymethylcellulose.no_majority":0.034016,"hydrolysis_carboxymethylcellulose.true":0.015703,"hydrolysis_carboxymethylcellulose.unannotated":0.896125,"hydrolysis_carboxymethylcellulose.unclassified":0.028831,"hydrolysis_casein.false":0.248443,"hydrolysis_casein.no_majority":0.242624,"hydrolysis_casein.true":0.309034,"hydrolysis_casein.unannotated":0.1662,"hydrolysis_casein.unclassified":0.028831,"hydrolysis_cationic_chitosan.false":0.004252,"hydrolysis_cationic_chitosan.unannotated":0.962049,"hydrolysis_cationic_chitosan.unclassified":0.028831,"hydrolysis_cellulose.false":0.033326,"hydrolysis_cellulose.no_majority":0.039088,"hydrolysis_cellulose.true":0.009269,"hydrolysis_cellulose.unannotated":0.884618,"hydrolysis_cellulose.unclassified":0.028831,"hydrolysis_chitin.false":0.016598,"hydrolysis_chitin.no_majority":0.026631,"hydrolysis_chitin.unannotated":0.923073,"hydrolysis_chitin.unclassified":0.028831,"hydrolysis_chitosan.false":0.000186,"hydrolysis_chitosan.unannotated":0.966115,"hydrolysis_chitosan.unclassified":0.028831,"hydrolysis_crystalline_cellulose.false":0.00097,"hydrolysis_crystalline_cellulose.unannotated":0.965331,"hydrolysis_crystalline_cellulose.unclassified":0.028831,"hydrolysis_dna.false":0.037802,"hydrolysis_dna.no_majority":0.002443,"hydrolysis_dna.unannotated":0.926056,"hydrolysis_dna.unclassified":0.028831,"hydrolysis_gelatin.false":0.220134,"hydrolysis_gelatin.no_majority":0.266532,"hydrolysis_gelatin.true":0.341986,"hydrolysis_gelatin.unannotated":0.137649,"hydrolysis_gelatin.unclassified":0.028831,"hydrolysis_skimmed_milk.false":0.000392,"hydrolysis_skimmed_milk.true":0.000802,"hydrolysis_skimmed_milk.unannotated":0.965108,"hydrolysis_skimmed_milk.unclassified":0.028831,"hydrolysis_starch.false":0.325128,"hydrolysis_starch.no_majority":0.278505,"hydrolysis_starch.true":0.195349,"hydrolysis_starch.unannotated":0.167319,"hydrolysis_starch.unclassified":0.028831,"hydrolysis_tween_20.false":0.021969,"hydrolysis_tween_20.true":0.00028,"hydrolysis_tween_20.unannotated":0.944053,"hydrolysis_tween_20.unclassified":0.028831,"hydrolysis_tween_40.false":0.012178,"hydrolysis_tween_40.unannotated":0.954123,"hydrolysis_tween_40.unclassified":0.028831,"hydrolysis_tween_60.false":0.012178,"hydrolysis_tween_60.unannotated":0.954123,"hydrolysis_tween_60.unclassified":0.028831,"hydrolysis_tween_80.false":0.001455,"hydrolysis_tween_80.no_majority":0.00248,"hydrolysis_tween_80.true":0.010182,"hydrolysis_tween_80.unannotated":0.952184,"hydrolysis_tween_80.unclassified":0.028831,"hydrolysis_urea.false":0.53217,"hydrolysis_urea.no_majority":0.312036,"hydrolysis_urea.true":0.000242,"hydrolysis_urea.unannotated":0.121853,"hydrolysis_urea.unclassified":0.028831,"hydrolysis_xylan.false":0.842527,"hydrolysis_xylan.unannotated":0.123774,"hydrolysis_xylan.unclassified":0.028831,"nitrification.false":0.823076,"nitrification.no_majority":0.000336,"nitrification.true":0.019115,"nitrification.unannotated":0.123774,"nitrification.unclassified":0.028831,"nitrogen_fixation.false":0.778654,"nitrogen_fixation.no_majority":0.003431,"nitrogen_fixation.true":0.060442,"nitrogen_fixation.unannotated":0.123774,"nitrogen_fixation.unclassified":0.028831,"nitrogen_source_ammonium.true":0.037858,"nitrogen_source_ammonium.unannotated":0.928444,"nitrogen_source_ammonium.unclassified":0.028831,"nitrogen_source_ammonium_chloride.true":0.004196,"nitrogen_source_ammonium_chloride.unannotated":0.962105,"nitrogen_source_ammonium_chloride.unclassified":0.028831,"nitrogen_source_ammonium_sulfate.false":0.002294,"nitrogen_source_ammonium_sulfate.true":0.010182,"nitrogen_source_ammonium_sulfate.unannotated":0.953825,"nitrogen_source_ammonium_sulfate.unclassified":0.028831,"nitrogen_source_nitrate.true":0.000709,"nitrogen_source_nitrate.unannotated":0.965592,"nitrogen_source_nitrate.unclassified":0.028831,"obligate_aerobic.false":0.091082,"obligate_aerobic.no_majority":0.123084,"obligate_aerobic.true":0.629406,"obligate_aerobic.unannotated":0.122729,"obligate_aerobic.unclassified":0.028831,"obligate_anaerobic.false":0.567155,"obligate_anaerobic.no_majority":0.192663,"obligate_anaerobic.true":0.083753,"obligate_anaerobic.unannotated":0.122729,"obligate_anaerobic.unclassified":0.028831,"oxidation_alpha_cyclodextrin.false":0.058595,"oxidation_alpha_cyclodextrin.unannotated":0.907706,"oxidation_alpha_cyclodextrin.unclassified":0.028831,"oxidation_ammonia.false":0.822293,"oxidation_ammonia.no_majority":0.010593,"oxidation_ammonia.true":0.009642,"oxidation_ammonia.unannotated":0.123774,"oxidation_ammonia.unclassified":0.028831,"oxidation_cellobiose.true":0.0265,"oxidation_cellobiose.unannotated":0.939801,"oxidation_cellobiose.unclassified":0.028831,"oxidation_elemental_sulfur.true":0.004886,"oxidation_elemental_sulfur.unannotated":0.961415,"oxidation_elemental_sulfur.unclassified":0.028831,"oxidation_in_darkness_iron.false":0.834415,"oxidation_in_darkness_iron.no_majority":0.008112,"oxidation_in_darkness_iron.unannotated":0.123774,"oxidation_in_darkness_iron.unclassified":0.028831,"oxidation_in_darkness_sulfide.false":0.84139,"oxidation_in_darkness_sulfide.no_majority":0.001138,"oxidation_in_darkness_sulfide.unannotated":0.123774,"oxidation_in_darkness_sulfide.unclassified":0.028831,"oxidation_in_darkness_sulfur_compounds.false":0.81806,"oxidation_in_darkness_sulfur_compounds.no_majority":0.009157,"oxidation_in_darkness_sulfur_compounds.true":0.015311,"oxidation_in_darkness_sulfur_compounds.unannotated":0.123774,"oxidation_in_darkness_sulfur_compounds.unclassified":0.028831,"oxidation_methanol.false":0.781638,"oxidation_methanol.no_majority":0.060889,"oxidation_methanol.unannotated":0.123774,"oxidation_methanol.unclassified":0.028831,"oxidation_sulfide.true":0.003767,"oxidation_sulfide.unannotated":0.962534,"oxidation_sulfide.unclassified":0.028831,"oxidation_thiosulfate.true":0.005222,"oxidation_thiosulfate.unannotated":0.961079,"oxidation_thiosulfate.unclassified":0.028831,"oxygen_preference.aerobic":0.423352,"oxygen_preference.no_majority":0.33848,"oxygen_preference.other":0.062306,"oxygen_preference.unannotated":0.142162,"oxygen_preference.unclassified":0.028831,"ph_growth.mean":6.925996,"ph_growth.unannotated":0.113107,"ph_growth.unclassified":0.028831,"ph_maximum.mean":8.747686,"ph_maximum.unannotated":0.025605,"ph_maximum.unclassified":0.028831,"ph_minimum.mean":5.23458,"ph_minimum.unannotated":0.025605,"ph_minimum.unclassified":0.028831,"ph_preference.alkaliphile":0.393066,"ph_preference.no_majority":0.017829,"ph_preference.other":0.049457,"ph_preference.unannotated":0.505949,"ph_preference.unclassified":0.028831,"presence_of_hemolysis.false":0.627933,"presence_of_hemolysis.no_majority":0.145015,"presence_of_hemolysis.true":0.025754,"presence_of_hemolysis.unannotated":0.167599,"presence_of_hemolysis.unclassified":0.028831,"presence_of_motility.false":0.227481,"presence_of_motility.no_majority":0.338499,"presence_of_motility.true":0.372217,"presence_of_motility.unannotated":0.028104,"presence_of_motility.unclassified":0.028831,"produces_cellulose.false":0.000429,"produces_cellulose.unannotated":0.965872,"produces_cellulose.unclassified":0.028831,"produces_dinitrogen.false":0.024132,"produces_dinitrogen.no_majority":0.020421,"produces_dinitrogen.unannotated":0.921748,"produces_dinitrogen.unclassified":0.028831,"produces_exopolysaccharide.true":0.016859,"produces_exopolysaccharide.unannotated":0.949442,"produces_exopolysaccharide.unclassified":0.028831,"produces_hydrogen_sulfide.false":0.508523,"produces_hydrogen_sulfide.no_majority":0.227481,"produces_hydrogen_sulfide.true":0.064358,"produces_hydrogen_sulfide.unannotated":0.165939,"produces_hydrogen_sulfide.unclassified":0.028831,"produces_indole_3_acetate.false":0.018612,"produces_indole_3_acetate.true":0.010182,"produces_indole_3_acetate.unannotated":0.937507,"produces_indole_3_acetate.unclassified":0.028831,"produces_indole_3_acetic_acid.false":0.058595,"produces_indole_3_acetic_acid.unannotated":0.907706,"produces_indole_3_acetic_acid.unclassified":0.028831,"produces_melanin.false":0.011842,"produces_melanin.no_majority":0.012346,"produces_melanin.unannotated":0.942113,"produces_melanin.unclassified":0.028831,"produces_methane_from_acetate.false":0.842527,"produces_methane_from_acetate.unannotated":0.123774,"produces_methane_from_acetate.unclassified":0.028831,"produces_methane_from_formate.false":0.842527,"produces_methane_from_formate.unannotated":0.123774,"produces_methane_from_formate.unclassified":0.028831,"produces_nitrate.false":0.004177,"produces_nitrate.unannotated":0.962124,"produces_nitrate.unclassified":0.028831,"produces_nitrite.false":0.041793,"produces_nitrite.true":0.003972,"produces_nitrite.unannotated":0.920536,"produces_nitrite.unclassified":0.028831,"produces_siderophore.true":0.016448,"produces_siderophore.unannotated":0.949853,"produces_siderophore.unclassified":0.028831,"psychrophilic.false":0.842527,"psychrophilic.unannotated":0.123774,"psychrophilic.unclassified":0.028831,"reduction_nitrate.false":0.216516,"reduction_nitrate.no_majority":0.593674,"reduction_nitrate.true":0.038678,"reduction_nitrate.unannotated":0.117433,"reduction_nitrate.unclassified":0.028831,"reduction_nitrite.false":0.560404,"reduction_nitrite.no_majority":0.124072,"reduction_nitrite.true":0.115027,"reduction_nitrite.unannotated":0.166797,"reduction_nitrite.unclassified":0.028831,"reduction_sulfate.false":0.000559,"reduction_sulfate.unannotated":0.965742,"reduction_sulfate.unclassified":0.028831,"required_for_growth_biotin.false":0.006788,"required_for_growth_biotin.unannotated":0.959513,"required_for_growth_biotin.unclassified":0.028831,"required_for_growth_cobalamin.true":0.05287,"required_for_growth_cobalamin.unannotated":0.913431,"required_for_growth_cobalamin.unclassified":0.028831,"required_for_growth_sodium_chloride.false":0.004606,"required_for_growth_sodium_chloride.true":0.000559,"required_for_growth_sodium_chloride.unannotated":0.961135,"required_for_growth_sodium_chloride.unclassified":0.028831,"respiration_alpha_cyclodextrin.false":0.003506,"respiration_alpha_cyclodextrin.unannotated":0.962795,"respiration_alpha_cyclodextrin.unclassified":0.028831,"respiration_beta_cyclodextrin.false":0.001212,"respiration_beta_cyclodextrin.unannotated":0.965089,"respiration_beta_cyclodextrin.unclassified":0.028831,"respiration_cellobiose.true":0.018742,"respiration_cellobiose.unannotated":0.947559,"respiration_cellobiose.unclassified":0.028831,"respiration_nitrate.false":0.097889,"respiration_nitrate.no_majority":0.021372,"respiration_nitrate.true":0.011376,"respiration_nitrate.unannotated":0.835664,"respiration_nitrate.unclassified":0.028831,"respiration_nitrogen.false":0.703778,"respiration_nitrogen.no_majority":0.125918,"respiration_nitrogen.true":0.012831,"respiration_nitrogen.unannotated":0.123774,"respiration_nitrogen.unclassified":0.028831,"salinity_growth.mean":1.030316,"salinity_growth.unannotated":0.028179,"salinity_growth.unclassified":0.028831,"salinity_maximum.mean":3.182038,"salinity_maximum.unannotated":0.028235,"salinity_maximum.unclassified":0.028831,"salinity_minimum.mean":0.285943,"salinity_minimum.unannotated":0.045727,"salinity_minimum.unclassified":0.028831,"salinity_preference.halotolerant":0.04224,"salinity_preference.no_majority":0.129238,"salinity_preference.other":0.077934,"salinity_preference.unannotated":0.716889,"salinity_preference.unclassified":0.028831,"sporulation.false":0.774253,"sporulation.no_majority":0.028757,"sporulation.true":0.126758,"sporulation.unannotated":0.036534,"sporulation.unclassified":0.028831,"temperature_growth.mean":32.361104,"temperature_growth.unannotated":0.011078,"temperature_growth.unclassified":0.028831,"temperature_maximum.mean":41.238682,"temperature_maximum.unannotated":0.024505,"temperature_maximum.unclassified":0.028831,"temperature_minimum.mean":17.70135,"temperature_minimum.unannotated":0.024505,"temperature_minimum.unclassified":0.028831,"temperature_preference.mesophilic":0.407053,"temperature_preference.no_majority":0.028757,"temperature_preference.other":0.011842,"temperature_preference.unannotated":0.518649,"temperature_preference.unclassified":0.028831,"thermophilic.false":0.83462,"thermophilic.no_majority":0.003711,"thermophilic.true":0.004196,"thermophilic.unannotated":0.123774,"thermophilic.unclassified":0.028831,"utilizes_casein.true":0.003972,"utilizes_casein.unannotated":0.962329,"utilizes_casein.unclassified":0.028831,"utilizes_cellobiose.true":0.016448,"utilizes_cellobiose.unannotated":0.949853,"utilizes_cellobiose.unclassified":0.028831,"utilizes_cellulose.false":0.008355,"utilizes_cellulose.no_majority":0.022565,"utilizes_cellulose.true":0.005147,"utilizes_cellulose.unannotated":0.930234,"utilizes_cellulose.unclassified":0.028831,"utilizes_gelatin.true":0.003972,"utilizes_gelatin.unannotated":0.962329,"utilizes_gelatin.unclassified":0.028831}