{"1a":{"top":[["Bradyrhizobium",0.008987],["Allocoleopsis",0.008866],["Shumkonia",0.002635]],"more":0},"1b":{"top":[["Nitrososphaera",0.053019],["Nitrosarchaeum",0.016556],["Bradyrhizobium",0.008987],["Nitrospira",0.00896],["Rhodoplanes",0.008271],["Lacipirellula",0.003068],["Shumkonia",0.002635],["Sulfurivermis",0.001919]],"more":3},"1c":{"top":[["Nitrosarchaeum",0.016556],["Terricaulis",0.00965],["Bradyrhizobium",0.008987],["Limibacillus",0.007622],["Skermanella",0.006582],["Mesobacillus",0.004676],["Pseudomarimonas",0.003217],["Hyphomicrobium",0.003014]],"more":59},"1d":{"top":[["Streptomyces",0.025733],["Sphingomonas",0.015164],["Devosia",0.007609],["Paenibacillus",0.006852],["Glaciimonas",0.006136],["Paractinoplanes",0.005906],["Proteus",0.004446],["Pseudarthrobacter",0.002825]],"more":29},"2":{"top":[["Brevitalea",0.051222],["Luteitalea",0.027476],["Gemmatimonas",0.025949],["Streptomyces",0.025733],["Povalibacter",0.024949],["Vicinamibacter",0.018272],["Sphingomonas",0.015164],["Gaiella",0.014502]],"more":382},"3a":{"top":[["Nitrososphaera",0.053019],["Luteitalea",0.027476],["Gemmatimonas",0.025949],["Streptomyces",0.025733],["Nitrosarchaeum",0.016556],["Sphingomonas",0.015164],["Gaiella",0.014502],["Chthoniobacter",0.012015]],"more":355},"3b":{"top":[["Luteitalea",0.027476],["Gemmatimonas",0.025949],["Streptomyces",0.025733],["Sphingomonas",0.015164],["Chthoniobacter",0.012015],["Allocoleopsis",0.008866],["Limisphaera",0.00846],["Actinoplanes",0.008271]],"more":214},"3c":{"top":[["Streptomyces",0.025733],["Pseudoalteromonas",0.006582],["Kribbella",0.002892],["Polycyclovorans",0.001338],["Novosphingobium",0.000757],["Hydrocarboniphaga",0.000527],["Acinetobacter",0.000351],["Alcanivorax",0.000297]],"more":5},"3d":{"top":[["Luteitalea",0.027476],["Gemmatimonas",0.025949],["Streptomyces",0.025733],["Sphingomonas",0.015164],["Gaiella",0.014502],["Chthoniobacter",0.012015],["Terricaulis",0.00965],["Bradyrhizobium",0.008987]],"more":332},"4":{"top":[["Allocoleopsis",0.008866],["Kallotenue",0.006122],["Polyangium",0.004906],["Lignipirellula",0.00446],["Proteus",0.004446],["Lacipirellula",0.003068],["Oscillochloris",0.003],["Urbifossiella",0.002798]],"more":54},"5":{"top":[["Methylobacterium",0.001243],["Methylocystis",0.000689],["Pseudomethylobacillus",0.000203]],"more":0},"6":{"top":[["Geoanaerobacter",0.0025],["Ferrimicrobium",0.000432],["Leptospirillum",0.000297],["Anaeromicrobium",0.00027]],"more":0},"7":{"top":[["Brevitalea",0.051222],["Luteitalea",0.027476],["Gemmatimonas",0.025949],["Streptomyces",0.025733],["Vicinamibacter",0.018272],["Sphingomonas",0.015164],["Tepidimonas",0.009096],["Bradyrhizobium",0.008987]],"more":251},"8":{"top":[["Streptomyces",0.025733],["Paenibacillus",0.006852],["Pseudomonas",0.001392]],"more":0},"9":{"top":[["Nitrosarchaeum",0.016556],["Allocoleopsis",0.008866],["Falsiroseomonas",0.008609],["Caldichromatium",0.002027],["Sulfurivermis",0.001919],["Nostoc",0.001541],["Methylobacterium",0.001243],["Clostridium",0.000811]],"more":9},"10":{"top":[["Nitrososphaera",0.053019],["Luteitalea",0.027476],["Gemmatimonas",0.025949],["Streptomyces",0.025733],["Nitrosarchaeum",0.016556],["Gaiella",0.014502],["Terricaulis",0.00965],["Tepidimonas",0.009096]],"more":300},"12":{"top":[["Paenibacillus",0.006852],["Skermanella",0.006582],["Microbacterium",0.002027],["Staphylococcus",0.000257]],"more":0}}